armcortnet/__init__.py
armcortnet/prediction.py
armcortnet/utils.py
armcortnet-0.6.0.dist-info/LICENSE
armcortnet-0.6.0.dist-info/METADATA
armcortnet-0.6.0.dist-info/WHEEL
armcortnet-0.6.0.dist-info/RECORD
