Metadata-Version: 2.3
Name: armcortnet
Version: 0.6.0
Summary: An automated deep learning pipeline for segmentation of the scapula, humerus, and their respective subregions in CT scans.
License: Apache License
Author: gspangenberg
Author-email: gspangen@uwo.ca
Requires-Python: >=3.11
Classifier: License :: Other/Proprietary License
Classifier: Programming Language :: Python :: 3
Classifier: Programming Language :: Python :: 3.11
Classifier: Programming Language :: Python :: 3.12
Classifier: Programming Language :: Python :: 3.13
Requires-Dist: armcrop (>=1.2.0)
Requires-Dist: huggingface-hub (>=0.25.1)
Requires-Dist: nnunetv2 (>=2.5)
Requires-Dist: simpleitkutilities (>=0.3.0)
Requires-Dist: vtk (>=9.0)
